miniball/__init__.py
miniball/bindings.cp39-win32.pyd
miniball/py.typed
MiniballCpp-0.2.3.dist-info/LICENSE
MiniballCpp-0.2.3.dist-info/METADATA
MiniballCpp-0.2.3.dist-info/WHEEL
MiniballCpp-0.2.3.dist-info/top_level.txt
MiniballCpp-0.2.3.dist-info/RECORD
