Metadata-Version: 2.1
Name: MiniballCpp
Version: 0.2.3
Summary: Smallest Enclosing Balls of Points
Home-page: https://github.com/weddige/miniball
Author: Bernd Gärtner, Konstantin Weddige
Classifier: License :: OSI Approved :: GNU General Public License v3 (GPLv3)
Classifier: Programming Language :: Python
Classifier: Topic :: Scientific/Engineering
Classifier: Topic :: Scientific/Engineering :: Mathematics
Classifier: Topic :: Software Development :: Libraries
Classifier: Topic :: Utilities
License-File: LICENSE
